{
  "generated": 231,
  "imdbDataset": {
    "withRating": 219,
    "withVotes": 219,
    "withGenre": 223,
    "missingRating": [
      "/program/26/cialo-teresy",
      "/program/26/czarna-godzina",
      "/program/26/dni-ktorych-nie-znamy",
      "/program/26/hot-spot",
      "/program/26/koszmarne-podszepty",
      "/program/26/nagly-przeblysk-slodyczy",
      "/program/26/noc-sie-dluzy",
      "/program/26/pozegnania",
      "/program/26/pucio",
      "/program/26/skarpetki-3",
      "/program/26/zatoka",
      "/program/26/zrodlo-zycia"
    ]
  },
  "skipped": [
    {
      "nhKey": "/program/26/1670-sezon-3",
      "title": "Netflix: 1670 (sezon 3) i otwarcie Panoramy 1670",
      "reason": "program bundle or non-film event"
    },
    {
      "nhKey": "/program/26/debata-shorty-na-festiwalach",
      "title": "Debata Shortlisty: Od pomysłu do Cannes. Jak zgłaszać się na festiwale?",
      "reason": "missing film metadata"
    },
    {
      "nhKey": "/program/26/dominik-gawronski-quartet",
      "title": "Dominik Gawroński Quartet - koncert",
      "reason": "missing film metadata"
    },
    {
      "nhKey": "/program/26/fejka-powered-by-tauron",
      "title": "Fejká powered by TAURON",
      "reason": "missing film metadata"
    },
    {
      "nhKey": "/program/26/fisz-ros-addiction-dj-set",
      "title": "Fisz & Ros Addiction (DJ set)",
      "reason": "missing film metadata"
    },
    {
      "nhKey": "/program/26/ho99o9",
      "title": "Ho99o9",
      "reason": "missing film metadata"
    },
    {
      "nhKey": "/program/26/ip-group-ambient-room-10-stratum",
      "title": "IP Group Ambient Room #10: STRATUM",
      "reason": "missing film metadata"
    },
    {
      "nhKey": "/program/26/maiden-w-hydropolis",
      "title": "Maiden w Hydropolis",
      "reason": "missing film metadata"
    },
    {
      "nhKey": "/program/26/masterclass-ewa-puszczynska",
      "title": "Jak powstaje kino światowego formatu? Masterclass z Ewą Puszczyńską",
      "reason": "missing film metadata"
    },
    {
      "nhKey": "/program/26/masterclass-lukasza-rondudy",
      "title": "Masterclass Łukasza Rondudy",
      "reason": "missing film metadata"
    },
    {
      "nhKey": "/program/26/masterclass-marie-kreutzer",
      "title": "Masterclass Marie Kreutzer",
      "reason": "missing film metadata"
    },
    {
      "nhKey": "/program/26/masterclass-ulrike-ottinger",
      "title": "Masterclass Ulrike Ottinger",
      "reason": "missing film metadata"
    },
    {
      "nhKey": "/program/26/nene-heroine",
      "title": "Nene Heroine",
      "reason": "missing film metadata"
    },
    {
      "nhKey": "/program/26/netflix-lalka",
      "title": "Netflix: Lalka",
      "reason": "program bundle or non-film event"
    },
    {
      "nhKey": "/program/26/otwarcie-sekcji-garden-party",
      "title": "Otwarcie sekcji Garden Party",
      "reason": "missing film metadata"
    },
    {
      "nhKey": "/program/26/pokaz-grand-prix",
      "title": "Pokaz laureata Grand Prix Międzynarodowego Konkursu Nowe Horyzonty",
      "reason": "missing film metadata"
    },
    {
      "nhKey": "/program/26/pokaz-nagrody-publicznosci",
      "title": "Pokaz laureata Nagrody Publiczności w Międzynarodowym Konkursie Nowe Horyzonty",
      "reason": "missing film metadata"
    },
    {
      "nhKey": "/program/26/seans-niespodzianka-w-renomie",
      "title": "Seans niespodzianka w Renomie",
      "reason": "missing film metadata"
    },
    {
      "nhKey": "/program/26/shortlista-zestaw-1",
      "title": "Długa przerwa",
      "reason": "program bundle or non-film event"
    },
    {
      "nhKey": "/program/26/shortlista-zestaw-2",
      "title": "Macocha",
      "reason": "program bundle or non-film event"
    },
    {
      "nhKey": "/program/26/shortlista-zestaw-3",
      "title": "Drewnojady",
      "reason": "program bundle or non-film event"
    },
    {
      "nhKey": "/program/26/speedfriending-ofelia-dj-set",
      "title": "Wieczór z Fundacją YES: Speedfriending + Ofelia (DJ set)",
      "reason": "missing film metadata"
    },
    {
      "nhKey": "/program/26/studio-bwa-wroclaw-gotycka-goraczka",
      "title": "Studio BWA Wrocław – Gotycka gorączka",
      "reason": "missing film metadata"
    },
    {
      "nhKey": "/program/26/twin-peaks-crew-hubert-zemler-roadhouse-band",
      "title": "Twin Peaks Crew – Hubert Zemler & Roadhouse Band",
      "reason": "missing film metadata"
    },
    {
      "nhKey": "/program/26/widzenie-peryferyjne-zestaw",
      "title": "Widzenie Peryferyjne - zestaw",
      "reason": "missing film metadata"
    },
    {
      "nhKey": "/program/26/zestaw-alego-cherriego",
      "title": "Strażnik",
      "reason": "program bundle or non-film event"
    }
  ],
  "lowConfidence": [
    {
      "nhKey": "/program/26/fukushima-z-bela-tarrem",
      "title": "Fukushima z Bélą Tarrem",
      "reason": "no high-confidence IMDb movie match",
      "alternatives": [
        {
          "id": "tt8185596",
          "title": "Béla Tarr: Regis Dialogue with Howard Feinstein",
          "year": 2008,
          "qid": "video",
          "rank": 493994,
          "credit": "Howard Feinstein, Béla Tarr",
          "query": "Fukushima with Béla Tarr",
          "score": 16
        }
      ],
      "candidate": {
        "id": "tt8185596",
        "title": "Béla Tarr: Regis Dialogue with Howard Feinstein",
        "year": 2008,
        "qid": "video",
        "rank": 493994,
        "credit": "Howard Feinstein, Béla Tarr",
        "query": "Fukushima with Béla Tarr",
        "score": 16
      }
    },
    {
      "nhKey": "/program/26/jesli-sie-przewroce-nie-podnos-mnie",
      "title": "Jeśli się przewrócę, nie podnoś mnie",
      "reason": "no high-confidence IMDb movie match",
      "alternatives": []
    },
    {
      "nhKey": "/program/26/kino-muranow",
      "title": "Kino Muranów",
      "reason": "no high-confidence IMDb movie match",
      "alternatives": [
        {
          "id": "tt1783244",
          "title": "Battle of Warsaw 1920",
          "year": 2011,
          "qid": "movie",
          "rank": 116060,
          "credit": "Daniel Olbrychski, Natasza Urbanska",
          "query": "La Muranów de Varsovie",
          "score": 16
        },
        {
          "id": "tt2236398",
          "title": "Shura no mure",
          "year": 1984,
          "qid": "movie",
          "rank": 312254,
          "credit": "Hiroki Matsukata, Wakako Sakai",
          "query": "Kino Muranów",
          "score": 16
        },
        {
          "id": "tt0454887",
          "title": "Ma cousine de Varsovie",
          "year": 1931,
          "qid": "movie",
          "rank": 364667,
          "credit": "Elvire Popesco, André Roanne",
          "query": "La Muranów de Varsovie",
          "score": 16
        },
        {
          "id": "tt1741534",
          "title": "High School Student Ruffian: The Sword of Muramasa",
          "year": 1973,
          "qid": "movie",
          "rank": 722854,
          "credit": "Masaaki Daimon, Yuriko Hishimi",
          "query": "Kino Muranów",
          "score": 16
        },
        {
          "id": "tt31040546",
          "title": "Shura no mure",
          "year": 2002,
          "qid": "movie",
          "rank": 765488,
          "credit": "Akira, Kyosuke Akita",
          "query": "Kino Muranów",
          "score": 16
        }
      ],
      "candidate": {
        "id": "tt1783244",
        "title": "Battle of Warsaw 1920",
        "year": 2011,
        "qid": "movie",
        "rank": 116060,
        "credit": "Daniel Olbrychski, Natasza Urbanska",
        "query": "La Muranów de Varsovie",
        "score": 16
      }
    },
    {
      "nhKey": "/program/26/lech-janerka-spij-spij-inteligencie",
      "title": "Lech Janerka – śpij, śpij, inteligencie",
      "reason": "no high-confidence IMDb movie match",
      "alternatives": []
    },
    {
      "nhKey": "/program/26/lionel",
      "title": "Lionel",
      "reason": "no high-confidence IMDb movie match",
      "alternatives": []
    },
    {
      "nhKey": "/program/26/natura",
      "title": "Natura",
      "reason": "no high-confidence IMDb movie match",
      "alternatives": [
        {
          "id": "tt0110632",
          "title": "Natural Born Killers",
          "year": 1994,
          "qid": "movie",
          "rank": 2642,
          "credit": "Woody Harrelson, Juliette Lewis",
          "query": "Natura",
          "score": 44
        },
        {
          "id": "tt0087781",
          "title": "The Natural",
          "year": 1984,
          "qid": "movie",
          "rank": 6350,
          "credit": "Robert Redford, Robert Duvall",
          "query": "Natura",
          "score": 44
        },
        {
          "id": "tt8211570",
          "title": "De Natura",
          "year": 2018,
          "qid": "short",
          "rank": 158607,
          "credit": "Maria Manta, Mihaela Manta",
          "query": "Natura",
          "score": 40
        },
        {
          "id": "tt32362890",
          "title": "Thrash",
          "year": 2026,
          "qid": "movie",
          "rank": 1109,
          "credit": "Phoebe Dynevor, Whitney Peak",
          "query": "Natura",
          "score": 20
        },
        {
          "id": "tt2629370",
          "title": "The Nude",
          "year": 2002,
          "qid": "movie",
          "rank": 137297,
          "credit": "Armen Adilkhanyan, Lyudmila Artemeva",
          "query": "Natura",
          "score": 16
        }
      ],
      "candidate": {
        "id": "tt0110632",
        "title": "Natural Born Killers",
        "year": 1994,
        "qid": "movie",
        "rank": 2642,
        "credit": "Woody Harrelson, Juliette Lewis",
        "query": "Natura",
        "score": 44
      }
    },
    {
      "nhKey": "/program/26/powiedz-mi-co-czujesz",
      "title": "Powiedz mi, co czujesz",
      "reason": "no high-confidence IMDb movie match",
      "alternatives": [
        {
          "id": "tt31723358",
          "title": "Tell Me What You Want",
          "year": 2024,
          "qid": "movie",
          "rank": 2466,
          "credit": "Gabriela Andrada, Mario Ermito",
          "query": "Tell Me How You Feel",
          "score": 20
        },
        {
          "id": "tt29142525",
          "title": "Tell Them You Love Me",
          "year": 2023,
          "qid": "movie",
          "rank": 20600,
          "credit": "Armani Cooper, Carl Hinson",
          "query": "Tell Me How You Feel",
          "score": 16
        },
        {
          "id": "tt39602504",
          "title": "Tell Me What You Feel",
          "year": 2026,
          "qid": "movie",
          "rank": 178279,
          "credit": "Jan Salasinski, Izabella Dudziak",
          "query": "Powiedz mi, co czujesz",
          "score": 16
        },
        {
          "id": "tt0809497",
          "title": "Tell Me You Love Me",
          "year": 2007,
          "qid": "tvSeries",
          "rank": 10336,
          "credit": "Michelle Borth, Tim DeKay",
          "query": "Tell Me How You Feel",
          "score": -31
        },
        {
          "id": "tt39375744",
          "title": "Tell Me What You Want",
          "year": 2026,
          "qid": "tvMiniSeries",
          "rank": 19908,
          "credit": "Kailey Merida, Shayne Davis",
          "query": "Tell Me How You Feel",
          "score": -31
        }
      ],
      "candidate": {
        "id": "tt31723358",
        "title": "Tell Me What You Want",
        "year": 2024,
        "qid": "movie",
        "rank": 2466,
        "credit": "Gabriela Andrada, Mario Ermito",
        "query": "Tell Me How You Feel",
        "score": 20
      }
    }
  ]
}
